{"textures":{"5":"modelengine:entity/oak_wood"},"elements":[{"from":[6.125,2.1500015,3.5],"to":[9.875,13.849998,12.499999],"faces":{"east":{"uv":[0.0,0.0,16.0,16.0],"tintindex":0,"rotation":0,"texture":"#5"},"south":{"uv":[0.0,2.4375,16.0,12.3125],"tintindex":0,"rotation":90,"texture":"#5"},"north":{"uv":[0.0,2.4375,16.0,12.3125],"tintindex":0,"rotation":90,"texture":"#5"},"west":{"uv":[0.0,0.0,16.0,16.0],"tintindex":0,"rotation":0,"texture":"#5"},"up":{"uv":[0.0,0.0,16.0,6.625],"tintindex":0,"rotation":270,"texture":"#5"},"down":{"uv":[0.0,0.0,16.0,6.625],"tintindex":0,"rotation":270,"texture":"#5"}}}],"display":{"gui":{"rotation":[30,225,0]}}}